bizai/utils/__init__.py
bizai/utils/app_enums.py
bizai/utils/attachment.py
bizai/utils/commonutils.py
bizai/utils/cosutils.py
bizai/utils/db2utils.py
bizai/utils/watson_nlu_utils.py
bizai/utils/watsondiscoveryutils.py
arunwagle_bizai_utils-0.0.7.dist-info/LICENSE
arunwagle_bizai_utils-0.0.7.dist-info/METADATA
arunwagle_bizai_utils-0.0.7.dist-info/WHEEL
arunwagle_bizai_utils-0.0.7.dist-info/top_level.txt
arunwagle_bizai_utils-0.0.7.dist-info/RECORD
