Metadata-Version: 2.1
Name: arunwagle-bizai-utils
Version: 0.0.7
Summary: Utils Package
Home-page: UNKNOWN
Author: Arun Wagle
Author-email: arun.wagle@ibm.com
License: UNKNOWN
Platform: UNKNOWN
Requires-Python: >=3.6
